[
  {
    "name": "Indexing",
    "url": "https://index.5pyd3r.org",
    "description": "Central index of all deployments and projects under 5pyd3r.org.",
    "category": "personal",
    "deployed_on": "Cloudflare Pages",
    "repo": "https://github.com/5pyd3r-labs/indexing",
    "status": "live",
    "tags": ["index", "directory", "static"]
  },
  {
    "name": "Portfolio",
    "url": "https://me.5pyd3r.org",
    "description": "Personal portfolio — projects, blog, and contact.",
    "category": "personal",
    "deployed_on": "Cloudflare Pages",
    "repo": "https://github.com/3rr0r-505/3rr0r-505.github.io",
    "status": "live",
    "tags": ["portfolio", "static", "personal"]
  },
  {
    "name": "Knowledge Base",
    "url": "https://lib.5pyd3r.org",
    "description": "Structured technical resources — networking, security, and beyond.",
    "category": "education",
    "deployed_on": "Cloudflare Pages",
    "repo": "https://github.com/5pyd3r-labs/knowledge-base",
    "status": "live",
    "tags": ["education", "resources", "reference"]
  }
]
